<?xml version="1.0" encoding="UTF-8"?>
<dataroot xmlns:od="urn:schemas-microsoft-com:officedata" xmlns:xsi="http://www.w3.org/2001/XMLSchema-instance"  xsi:noNamespaceSchemaLocation="Cast.xsd" generated="2019-05-23T09:30:47">
<Cast>
<ID>24</ID>
<Identifier>Adimarius2</Identifier>
<Location>Archives Nationales, Paris</Location>
<Accession_x002F_Collection_x0020_number>Service des Sceaux; SC/Collection Douët d&apos;Arcq 6201</Accession_x002F_Collection_x0020_number>
<Colour_x0020_1>uncoloured</Colour_x0020_1>
<Colour_x0020_2>uncoloured</Colour_x0020_2>
<Material>plaster</Material>
<Surface>varnished</Surface>
<Surround>none</Surround>
<Condition_x003A__x0020_fineness>fine</Condition_x003A__x0020_fineness>
<Condition_x003A__x0020_completeness>complete</Condition_x003A__x0020_completeness>
<Covering>none</Covering>
<Notes>L. Douët d&apos;Arcq, &apos;La Collection des Sceaux&apos;, vol. 2, p. 441, no. 6201.  Original in Arch. de l&apos;Emp. L 361.  &apos;Appendu à une bulle du cardinal en faveur de l&apos;hôpital des Haudriettes, datée de Paris, 18 des calendes de mai de l&apos;an 4 du pontificat de Jean XXIII (14 avril 1415).&apos;</Notes>
<MyImage>Allemanus1AN.jpg</MyImage>
<Height>83</Height>
<Width>58</Width>
<Figure_x0020_number>26</Figure_x0020_number>
</Cast>
<Cast>
<ID>25</ID>
<Identifier>Adimarius3</Identifier>
<Location>Archives Nationales, Paris</Location>
<Accession_x002F_Collection_x0020_number>Service des Sceaux; SC/Collection Douët d&apos;Arcq 6202</Accession_x002F_Collection_x0020_number>
<Colour_x0020_1>uncoloured</Colour_x0020_1>
<Colour_x0020_2>uncoloured</Colour_x0020_2>
<Material>plaster</Material>
<Surface>varnished</Surface>
<Surround>none</Surround>
<Condition_x003A__x0020_fineness>fine</Condition_x003A__x0020_fineness>
<Condition_x003A__x0020_completeness>damage to legend</Condition_x003A__x0020_completeness>
<Covering>none</Covering>
<Notes>Douët d&apos;Arcq, L., &apos;Collection de Sceaux&apos;, vol. 2, p. 441, no. 6202.  Original held in Arch. de l&apos;Emp. K 53, no. 18 bis.  &apos;Appendu à une bulle du cardinal, datée de Paris, 18 des calendes de mai de l&apos;an 4 du pontificat de Jean XXII (14 avril 1415), vidimant des lettres de Charles VI, datées d&apos;Orléans, avril après Pâques, qui donnent le gouvernement de l&apos;hôpital des Haudriettes au grand aumônier. - Nota.  Il est à remarquer que le cardinal scelle le même jour avec deux sceaux tout à fait différents.&apos;</Notes>
<MyImage>Allemanus2AN.jpg</MyImage>
<Height>80</Height>
<Width>56</Width>
<Figure_x0020_number>27</Figure_x0020_number>
</Cast>
<Cast>
<ID>22</ID>
<Identifier>AigrefeuilleF1</Identifier>
<Location>Archives Nationales, Paris</Location>
<Accession_x002F_Collection_x0020_number>Service des Sceaux; SC/Champagne 1449</Accession_x002F_Collection_x0020_number>
<Colour_x0020_1>uncoloured</Colour_x0020_1>
<Colour_x0020_2>uncoloured</Colour_x0020_2>
<Material>plaster</Material>
<Surface>plain</Surface>
<Surround>none</Surround>
<Condition_x003A__x0020_fineness>clear</Condition_x003A__x0020_fineness>
<Condition_x003A__x0020_completeness>damage to design and legend</Condition_x003A__x0020_completeness>
<Covering>none</Covering>
<Notes>Cast from a wax impression in the Archives de la Aube.</Notes>
<MyImage>AigrefeuilleF1AN.jpg</MyImage>
<Height>85</Height>
<Figure_x0020_number>14</Figure_x0020_number>
</Cast>
<Cast>
<ID>23</ID>
<Identifier>AlbretL1</Identifier>
<Location>Archives Nationales, Paris</Location>
<Accession_x002F_Collection_x0020_number>Service des Sceaux; SC/Collection Douët d&apos;Arcq 6209</Accession_x002F_Collection_x0020_number>
<Colour_x0020_1>uncoloured</Colour_x0020_1>
<Colour_x0020_2>uncoloured</Colour_x0020_2>
<Material>plaster</Material>
<Surface>varnished</Surface>
<Surround>none</Surround>
<Condition_x003A__x0020_fineness>clear</Condition_x003A__x0020_fineness>
<Condition_x003A__x0020_completeness>damage to legend</Condition_x003A__x0020_completeness>
<Covering>none</Covering>
<Notes>M. Douët d&apos;Arcq, &apos;La Collection des Sceaux&apos;, vol. 2, pp. 442-443, no. 6209.  Original held in Arch. de l&apos;Emp. L 368.  &apos;Même provenance que le numéro 6206&apos;.</Notes>
<MyImage>AlbretL1AN.jpg</MyImage>
<Height>95</Height>
<Width>62</Width>
<Figure_x0020_number>48</Figure_x0020_number>
</Cast>
<Cast>
<ID>27</ID>
<Identifier>Amboise1</Identifier>
<Location>Archives Nationales, Paris</Location>
<Accession_x002F_Collection_x0020_number>Service des Sceaux; SC/Normandie 2156</Accession_x002F_Collection_x0020_number>
<Colour_x0020_1>uncoloured</Colour_x0020_1>
<Colour_x0020_2>uncoloured</Colour_x0020_2>
<Material>plaster</Material>
<Surface>varnished</Surface>
<Surround>none</Surround>
<Condition_x003A__x0020_fineness>clear</Condition_x003A__x0020_fineness>
<Condition_x003A__x0020_completeness>damage to design and legend</Condition_x003A__x0020_completeness>
<Covering>none</Covering>
<Notes>Cat. no. 2156, from a detached seal in the Musee de Rouen.</Notes>
<MyImage>AmboiseG3AN.jpg</MyImage>
<Height>85</Height>
<Width>65</Width>
<Figure_x0020_number>66</Figure_x0020_number>
</Cast>
<Cast>
<ID>30</ID>
<Identifier>BarboM1</Identifier>
<Location>Archives Nationales, Paris</Location>
<Accession_x002F_Collection_x0020_number>Service des Sceaux; SC/Champagne 1457</Accession_x002F_Collection_x0020_number>
<Colour_x0020_1>uncoloured</Colour_x0020_1>
<Colour_x0020_2>uncoloured</Colour_x0020_2>
<Material>plaster</Material>
<Surface>plain</Surface>
<Surround>none</Surround>
<Condition_x003A__x0020_fineness>fine</Condition_x003A__x0020_fineness>
<Condition_x003A__x0020_completeness>complete</Condition_x003A__x0020_completeness>
<Covering>plastic cover</Covering>
<Notes>Held in the Archives Nationales, Champagne no. 1457.  &apos;Sceau en navette, de 93 et 51 mill. sur cordelettes de chanvre.  Cire vermeille dans une cuvette de cire vierge et boîte  de fer blanc.- Arch. de la Marne, G / 404, coll. Roserot nº 346 (incomplet).&apos;</Notes>
<MyImage>BarboM1AN.jpg</MyImage>
<Height>93</Height>
<Width>51</Width>
<Figure_x0020_number>51</Figure_x0020_number>
</Cast>
<Cast>
<ID>31</ID>
<Identifier>BarboM2</Identifier>
<Location>Archives Nationales, Paris</Location>
<Accession_x002F_Collection_x0020_number>Service des Sceaux; SC/Champagne 1464</Accession_x002F_Collection_x0020_number>
<Colour_x0020_1>uncoloured</Colour_x0020_1>
<Colour_x0020_2>uncoloured</Colour_x0020_2>
<Material>plaster</Material>
<Surface>plain</Surface>
<Surround>none</Surround>
<Condition_x003A__x0020_fineness>poor</Condition_x003A__x0020_fineness>
<Condition_x003A__x0020_completeness>damage to design and legend</Condition_x003A__x0020_completeness>
<Covering>plastic cover</Covering>
<Notes>Held in Archives Nationales Champagne no. 1464.</Notes>
<MyImage>BarboM2AN.jpg</MyImage>
<Width>61</Width>
<Figure_x0020_number>52</Figure_x0020_number>
</Cast>
<Cast>
<ID>32</ID>
<Identifier>BarL1</Identifier>
<Location>Archives Nationales, Paris</Location>
<Accession_x002F_Collection_x0020_number>Service des Sceaux; SC/Champagne 1451</Accession_x002F_Collection_x0020_number>
<Colour_x0020_1>uncoloured</Colour_x0020_1>
<Colour_x0020_2>uncoloured</Colour_x0020_2>
<Material>plaster</Material>
<Surface>plain</Surface>
<Surround>none</Surround>
<Condition_x003A__x0020_fineness>clear</Condition_x003A__x0020_fineness>
<Condition_x003A__x0020_completeness>damage to design and legend</Condition_x003A__x0020_completeness>
<Covering>plastic cover</Covering>
<Notes>Held in Archives Nationales Champagne no. 1451.  &apos;Cardinal-diacre de Sainte-Agathe, “administrator 		perpetuus episcopatus et ducatus Lingonensis” – 1403.
	Fragment d’un sceau en navette, de 85 et 62 mill., sur lacs de soie rouge. Cire vermeille dans une cuvette de cire vierge.- Arch. de la Haute Marne, carton réservé 2, H Val des Ecoliers.&apos;  Inventaire des Sceaux de la Champagne, 1451. Size: 85 x 62.</Notes>
<MyImage>BarL1AN.jpg</MyImage>
<Figure_x0020_number>21</Figure_x0020_number>
</Cast>
<Cast>
<ID>33</ID>
<Identifier>BarL2</Identifier>
<Location>Archives Nationales, Paris</Location>
<Accession_x002F_Collection_x0020_number>Service des Sceaux; SC/Collection Douët d&apos;Arcq 6199</Accession_x002F_Collection_x0020_number>
<Colour_x0020_1>uncoloured</Colour_x0020_1>
<Colour_x0020_2>uncoloured</Colour_x0020_2>
<Material>plaster</Material>
<Surface>plain</Surface>
<Surround>none</Surround>
<Condition_x003A__x0020_fineness>fine</Condition_x003A__x0020_fineness>
<Condition_x003A__x0020_completeness>slight damage to design and legend</Condition_x003A__x0020_completeness>
<Covering>plastic cover</Covering>
<Notes>L. Douët d&apos;Arcq, &apos;La Collection des Sceaux&apos;, vol. 2, p. 441, no. 6199.  Original in Arch. de l&apos;Emp.  L 846.  &apos;Appendu à une confirmation des priviléges de la Saint-Chapelle du Palai, datée de Boissy, 5 des nones de novembre, l&apos;an 1er du pontificat d&apos;Alexandre V (1er novembre 1409).&apos;</Notes>
<MyImage>BarL2AN.jpg</MyImage>
<Width>67</Width>
<Figure_x0020_number>22</Figure_x0020_number>
</Cast>
<Cast>
<ID>35</ID>
<Identifier>Bessarion1</Identifier>
<Location>Archives Nationales, Paris</Location>
<Accession_x002F_Collection_x0020_number>Service des Sceaux; SC/Champagne 1462</Accession_x002F_Collection_x0020_number>
<Colour_x0020_1>uncoloured</Colour_x0020_1>
<Colour_x0020_2>uncoloured</Colour_x0020_2>
<Material>plaster</Material>
<Surface>plain</Surface>
<Surround>none</Surround>
<Condition_x003A__x0020_fineness>faint</Condition_x003A__x0020_fineness>
<Condition_x003A__x0020_completeness>damage to design and legend</Condition_x003A__x0020_completeness>
<Covering>none</Covering>
<Notes>Held in Archives Nationales Champagne no. 1462.  &apos;Fragment d’un sceau en navette, de 80 et 54 mill. environ, sur / cordelettes de soie rose.  Cire vermeille dans une cuvette de parchemin.- / Arch. de la Haute-Marne ; (G. chapitre de Joinville G. 97) ; coll. Roserot / n° 350 (ancienne cote 413).&apos;</Notes>
<MyImage>Bessarion1AN.jpg</MyImage>
<Figure_x0020_number>41</Figure_x0020_number>
</Cast>
<Cast>
<ID>71</ID>
<Identifier>BlauP1</Identifier>
<Location>Archives Nationales, Paris</Location>
<Accession_x002F_Collection_x0020_number>Service des Sceaux; SC/Flandre 5746</Accession_x002F_Collection_x0020_number>
<Colour_x0020_1>uncoloured</Colour_x0020_1>
<Colour_x0020_2>uncoloured</Colour_x0020_2>
<Material>plaster</Material>
<Surface>plain</Surface>
<Surround>none</Surround>
<Condition_x003A__x0020_fineness>clear</Condition_x003A__x0020_fineness>
<Condition_x003A__x0020_completeness>slight damage to legend</Condition_x003A__x0020_completeness>
<Covering>none</Covering>
<Notes>Held in Archives Nationales Flandre no. 5746.  Arch. du Nord; évêché et chapitre de Cambrai.  Absolution du procureur du chapitre de Cambrai, qui avait été ex-communié par l’official de Reims. – Avignon, 19 mars 1404.</Notes>
<MyImage>BlauP1.jpg</MyImage>
<Height>77</Height>
<Width>51</Width>
<Figure_x0020_number>18</Figure_x0020_number>
</Cast>
<Cast>
<ID>38</ID>
<Identifier>CapranicaA1</Identifier>
<Location>Archives Nationales, Paris</Location>
<Accession_x002F_Collection_x0020_number>Service des Sceaux; SC/Champagne 1456</Accession_x002F_Collection_x0020_number>
<Colour_x0020_1>uncoloured</Colour_x0020_1>
<Colour_x0020_2>uncoloured</Colour_x0020_2>
<Material>plaster</Material>
<Surface>plain</Surface>
<Surround>none</Surround>
<Condition_x003A__x0020_fineness>clear</Condition_x003A__x0020_fineness>
<Condition_x003A__x0020_completeness>slight damage to legend</Condition_x003A__x0020_completeness>
<Covering>plastic cover</Covering>
<Notes>Held in Archives Nationales Champagne no. 1456</Notes>
<MyImage>CapranicaA1AN.jpg</MyImage>
<Height>90</Height>
<Width>55</Width>
<Figure_x0020_number>46</Figure_x0020_number>
</Cast>
<Cast>
<ID>39</ID>
<Identifier>CarafaO1</Identifier>
<Location>Archives Nationales, Paris</Location>
<Accession_x002F_Collection_x0020_number>Service des Sceaux; SC/Champagne 1459</Accession_x002F_Collection_x0020_number>
<Colour_x0020_1>uncoloured</Colour_x0020_1>
<Colour_x0020_2>uncoloured</Colour_x0020_2>
<Material>plaster</Material>
<Surface>plain</Surface>
<Surround>none</Surround>
<Condition_x003A__x0020_fineness>clear</Condition_x003A__x0020_fineness>
<Condition_x003A__x0020_completeness>damage to design and legend</Condition_x003A__x0020_completeness>
<Covering>plastic cover</Covering>
<Notes>Held in Archives Nationales Champagne no. 1459.  &apos;Fragment d’un sceau en navette, de 100 et 62 mill. environ, / sur cordelettes de chanvre rouges.  Cire vermeille dans une cuvette de / cire vierge.- Arch. de la Haute, chapitre de Joinville, G 97.- / Douet d’Arcq, nº 6213.-col. Roserot nº 348 [ . . . ]  Le sceau donné par Douet d’Arcq est celui dont Olivier Carrafa / se servit alors qu’il était cardinal du titre des Saints-Marcellin-et- / Pierre en 1470.  Il ne paraît pas différent, autant qu’on en peut juger / par le faible fragment qui subsiste et don’t la légende ne porte plus que / le mot Neapolitani, de celui que nous donnons ici et que le prélat / employa lorsqu’il fut devenu cardinal de Saint-Eusèbe.  Cette promotion / ayant eu lieu le 5 septembre 1470, il est possible qu’il n’ait pas encore / eu le temps de se faire graver un nouveau sceau, ou bien aura-t-il conser- / vé un sceau don’t la légende portait simplement = cardinalis Neapolitani, / sans préciser le titre, et qui par conséquent pouvait étre considéré comme / encore valable.&apos;  Size: 100 x 62?</Notes>
<MyImage>CarafaO1AN.jpg</MyImage>
<Figure_x0020_number>53</Figure_x0020_number>
</Cast>
<Cast>
<ID>99</ID>
<Identifier>Carvajal1</Identifier>
<Location>Society of Antiquaries, London</Location>
<Accession_x002F_Collection_x0020_number>Seal Cast Collection; Drawer G1</Accession_x002F_Collection_x0020_number>
<Colour_x0020_1>brown</Colour_x0020_1>
<Colour_x0020_2>brown</Colour_x0020_2>
<Material>plaster</Material>
<Surface>varnished</Surface>
<Surround>none</Surround>
<Condition_x003A__x0020_fineness>fine</Condition_x003A__x0020_fineness>
<Condition_x003A__x0020_completeness>complete</Condition_x003A__x0020_completeness>
<Covering>none</Covering>
<MyImage>CarvajalSOAcast.jpg</MyImage>
<Height>105</Height>
<Width>60</Width>
<Figure_x0020_number>6</Figure_x0020_number>
</Cast>
<Cast>
<ID>40</ID>
<Identifier>CarvajalB1</Identifier>
<Location>Archives Nationales, Paris</Location>
<Accession_x002F_Collection_x0020_number>Service des Sceaux; SC/Collection Douët d&apos;Arcq 6219</Accession_x002F_Collection_x0020_number>
<Colour_x0020_1>uncoloured</Colour_x0020_1>
<Colour_x0020_2>uncoloured</Colour_x0020_2>
<Material>plaster</Material>
<Surface>plain</Surface>
<Surround>none</Surround>
<Condition_x003A__x0020_fineness>faint</Condition_x003A__x0020_fineness>
<Condition_x003A__x0020_completeness>damage to design and legend</Condition_x003A__x0020_completeness>
<Covering>none</Covering>
<Notes>Held in Archives Nationales Douet d&apos;Arcq no. 6219</Notes>
<MyImage>CarvajalB1AN.jpg</MyImage>
<Figure_x0020_number>65</Figure_x0020_number>
</Cast>
<Cast>
<ID>41</ID>
<Identifier>CastiglioneB1</Identifier>
<Location>Archives Nationales, Paris</Location>
<Accession_x002F_Collection_x0020_number>Service des Sceaux; SC/Normandie 2154</Accession_x002F_Collection_x0020_number>
<Colour_x0020_1>uncoloured</Colour_x0020_1>
<Colour_x0020_2>uncoloured</Colour_x0020_2>
<Material>plaster</Material>
<Surface>plain</Surface>
<Surround>none</Surround>
<Condition_x003A__x0020_fineness>clear</Condition_x003A__x0020_fineness>
<Condition_x003A__x0020_completeness>complete</Condition_x003A__x0020_completeness>
<Covering>plastic cover</Covering>
<Notes>Held in Archives Nationales Normandie no. 2154</Notes>
<MyImage>CastiglioneB1AN.jpg</MyImage>
<Height>88</Height>
<Width>55</Width>
<Figure_x0020_number>28</Figure_x0020_number>
</Cast>
<Cast>
<ID>44</ID>
<Identifier>Challant1</Identifier>
<Location>Archives Nationales, Paris</Location>
<Accession_x002F_Collection_x0020_number>Service des Sceaux; SC/Normandie 2153</Accession_x002F_Collection_x0020_number>
<Colour_x0020_1>uncoloured</Colour_x0020_1>
<Colour_x0020_2>uncoloured</Colour_x0020_2>
<Material>plaster</Material>
<Surface>plain</Surface>
<Surround>none</Surround>
<Condition_x003A__x0020_fineness>fine</Condition_x003A__x0020_fineness>
<Condition_x003A__x0020_completeness>damage to design and legend</Condition_x003A__x0020_completeness>
<Covering>plastic cover</Covering>
<Notes>Demay, G, &apos;Inventaire des Sceaux de la Normandie&apos;, no. 2153, p. 231.  Original held in Arch. De la Seine-Inférieure; chapitre de Rouen: &apos;Délégation de pouvoirs pour réconcilier les églises et les cimetières qui auraient été souilles - Juin 1405.&apos;</Notes>
<MyImage>ChallantA1ANa.jpg</MyImage>
<Figure_x0020_number>24</Figure_x0020_number>
</Cast>
<Cast>
<ID>17</ID>
<Identifier>CiboI1</Identifier>
<Location>Musée du Louvre, Paris</Location>
<Accession_x002F_Collection_x0020_number>Della Torre Aile Richelieu.  Premier étage: Section 13, vitrine V03.</Accession_x002F_Collection_x0020_number>
<Colour_x0020_1>uncoloured</Colour_x0020_1>
<Colour_x0020_2>uncoloured</Colour_x0020_2>
<Material>bronze</Material>
<Surface>gilt</Surface>
<Surround>none</Surround>
<Condition_x003A__x0020_fineness>fine</Condition_x003A__x0020_fineness>
<Condition_x003A__x0020_completeness>complete</Condition_x003A__x0020_completeness>
<Covering>none</Covering>
<Notes>Musée du Louvre.  Della Torre Aile Richelieu.  Premier étage - Section 13, vitrine V03.  Piet-Lautadrie bequest (1915).</Notes>
<MyImage>Cibo1.jpg</MyImage>
<Height>115</Height>
<Width>70</Width>
<Figure_x0020_number>80</Figure_x0020_number>
</Cast>
<Cast>
<ID>81</ID>
<Identifier>ClermontF1</Identifier>
<Location>Archives Nationales, Paris</Location>
<Accession_x002F_Collection_x0020_number>Service des Sceaux; SC/Supplement 5239</Accession_x002F_Collection_x0020_number>
<Colour_x0020_1>uncoloured</Colour_x0020_1>
<Colour_x0020_2>uncoloured</Colour_x0020_2>
<Material>plaster</Material>
<Surface>plain</Surface>
<Surround>none</Surround>
<Condition_x003A__x0020_fineness>faint</Condition_x003A__x0020_fineness>
<Condition_x003A__x0020_completeness>damage to design and legend</Condition_x003A__x0020_completeness>
<Covering>none</Covering>
<Notes>Held in Archives Nationales Supplement no. 5239</Notes>
<MyImage>Supplement5239.jpg</MyImage>
<Figure_x0020_number>70</Figure_x0020_number>
</Cast>
<Cast>
<ID>46</ID>
<Identifier>CoetivyA1</Identifier>
<Location>Archives Nationales, Paris</Location>
<Accession_x002F_Collection_x0020_number>Service des Sceaux; SC/Collection Douët d&apos;Arcq 6207</Accession_x002F_Collection_x0020_number>
<Colour_x0020_1>uncoloured</Colour_x0020_1>
<Colour_x0020_2>uncoloured</Colour_x0020_2>
<Material>plaster</Material>
<Surface>plain</Surface>
<Surround>none</Surround>
<Condition_x003A__x0020_fineness>clear</Condition_x003A__x0020_fineness>
<Condition_x003A__x0020_completeness>damage to design and legend</Condition_x003A__x0020_completeness>
<Covering>none</Covering>
<Notes>M. Douët d&apos;Arcq, &apos;La Collection des Sceaux&apos;, vol. 2, p. 442, no. 6207.  Original held in Arch. de l&apos;Emp. L 368.  Même provenance que le numéro 6206.</Notes>
<MyImage>CoetivyA1AN.jpg</MyImage>
<Height>112</Height>
<Width>65</Width>
<Figure_x0020_number>40</Figure_x0020_number>
</Cast>
<Cast>
<ID>48</ID>
<Identifier>EpinayA1</Identifier>
<Location>Archives Nationales, Paris</Location>
<Accession_x002F_Collection_x0020_number>Service des Sceaux; SC/Collection Douët d&apos;Arcq 6215</Accession_x002F_Collection_x0020_number>
<Colour_x0020_1>uncoloured</Colour_x0020_1>
<Colour_x0020_2>uncoloured</Colour_x0020_2>
<Material>plaster</Material>
<Surface>plain</Surface>
<Surround>none</Surround>
<Condition_x003A__x0020_fineness>fine</Condition_x003A__x0020_fineness>
<Condition_x003A__x0020_completeness>complete</Condition_x003A__x0020_completeness>
<Covering>none</Covering>
<Notes>M. Douët d&apos;Arcq, &apos;La Collection des Sceaux&apos;, vol. 2, p. 443, no. 6215.  Original held in Arch. de l&apos;Emp. L 1450.  &apos;Appendu à une charte datée de Lyon, 14 juillet 1497.&apos;</Notes>
<MyImage>EpinayA1AN.jpg</MyImage>
<Height>88</Height>
<Width>62</Width>
<Figure_x0020_number>63</Figure_x0020_number>
</Cast>
<Cast>
<ID>49</ID>
<Identifier>EstoutevilleG1</Identifier>
<Location>Archives Nationales, Paris</Location>
<Accession_x002F_Collection_x0020_number>Service des Sceaux; SC/Champagne 1455</Accession_x002F_Collection_x0020_number>
<Colour_x0020_1>uncoloured</Colour_x0020_1>
<Colour_x0020_2>uncoloured</Colour_x0020_2>
<Material>plaster</Material>
<Surface>plain</Surface>
<Surround>none</Surround>
<Condition_x003A__x0020_fineness>fine</Condition_x003A__x0020_fineness>
<Condition_x003A__x0020_completeness>complete</Condition_x003A__x0020_completeness>
<Covering>plastic cover</Covering>
<Notes>Held in Archives Nationales Champagne 1455</Notes>
<MyImage>EstoutevilleG1AN.jpg</MyImage>
<Height>75</Height>
<Width>45</Width>
<Figure_x0020_number>39</Figure_x0020_number>
</Cast>
<Cast>
<ID>94</ID>
<Identifier>EstoutevilleG2</Identifier>
<Location>Archives Nationales, Paris</Location>
<Accession_x002F_Collection_x0020_number>Service des Sceaux; SC/Collection Douët d&apos;Arcq 6206</Accession_x002F_Collection_x0020_number>
<Colour_x0020_1>uncoloured</Colour_x0020_1>
<Colour_x0020_2>uncoloured</Colour_x0020_2>
<Material>plaster</Material>
<Surface>varnished</Surface>
<Surround>none</Surround>
<Condition_x003A__x0020_fineness>clear</Condition_x003A__x0020_fineness>
<Condition_x003A__x0020_completeness>damage to legend</Condition_x003A__x0020_completeness>
<Covering>none</Covering>
<Notes>Copy of the cast provded by the Service des Sceaux, Archives Nationales de France, Paris.  M. Douët d&apos;Arcq, &apos;La Collection des Sceaux&apos;, vol. 2, p. 442, no. 6206.  Original held in Arch. de l&apos;Emp. L 368.  &apos;Appendu à une bulle de cinq cardinaux, donnée à Rome le 20 dicembre 1463, concédant des indulgences à ceux qui contribueront aux frais des réparations de la chartreuse de Vauvert, hors Paris.&apos;</Notes>
<MyImage>EstoutevilleG2AN.jpg</MyImage>
<Height>93</Height>
<Width>58</Width>
<Figure_x0020_number>47</Figure_x0020_number>
</Cast>
<Cast>
<ID>70</ID>
<Identifier>FoixP2</Identifier>
<Location>Archives Nationales, Paris</Location>
<Accession_x002F_Collection_x0020_number>Service des Sceaux; SC/Flandre 5753</Accession_x002F_Collection_x0020_number>
<Colour_x0020_1>uncoloured</Colour_x0020_1>
<Colour_x0020_2>uncoloured</Colour_x0020_2>
<Material>plaster</Material>
<Surface>plain</Surface>
<Surround>none</Surround>
<Condition_x003A__x0020_fineness>clear</Condition_x003A__x0020_fineness>
<Condition_x003A__x0020_completeness>damage to design and legend</Condition_x003A__x0020_completeness>
<Covering>none</Covering>
<Notes>Held in Archives Nationales Flandre 5753. Demay, G., &apos;Inventaire des Sceaux de la Flandre&apos;, vol. 2, no. 5753, p. 103.  Original held in Arch. du Nord, évêché et chapitre de Cambrai. &apos;Copie de la bulle d&apos;Urbain V relative à la diminution de la dime. - Carpentras, 2 juillet 1442.&apos;</Notes>
<MyImage>Pierre3AN.jpg</MyImage>
<Height>90</Height>
<Width>56</Width>
<Figure_x0020_number>37</Figure_x0020_number>
</Cast>
<Cast>
<ID>15</ID>
<Identifier>GonzagaE1</Identifier>
<Location>Ranger&apos;s House, London</Location>
<Accession_x002F_Collection_x0020_number>Wernher Collection</Accession_x002F_Collection_x0020_number>
<Colour_x0020_1>uncoloured</Colour_x0020_1>
<Colour_x0020_2>uncoloured</Colour_x0020_2>
<Material>bronze</Material>
<Surface>gold</Surface>
<Surround>none</Surround>
<Condition_x003A__x0020_fineness>fine</Condition_x003A__x0020_fineness>
<Condition_x003A__x0020_completeness>complete</Condition_x003A__x0020_completeness>
<Covering>none</Covering>
<Notes>Gilt bronze cast possibly of original presentation model by Benvenuto Cellini.  Inscription: &apos;ASVMPTA. EST/ MARIA. INC/ OELVM&apos; [Asumpta est Maria in Coelum]. Gilt bronze plaquette in the Wernher Collection. Photographs: EE 28788259449, negative no. D49, English Heritage picture number K011209, Nov. 2001 by Jonathan Bailey.

Possibly a cast of the original presentation model by Benvenuto Cellini.</Notes>
<MyImage>GonzagaE1RH01.jpg</MyImage>
<Height>105</Height>
<Width>65</Width>
<Figure_x0020_number>4</Figure_x0020_number>
</Cast>
<Cast>
<ID>55</ID>
<Identifier>Guillaume1</Identifier>
<Location>Archives Nationales, Paris</Location>
<Accession_x002F_Collection_x0020_number>Service des Sceaux; SC/Flandre 5755</Accession_x002F_Collection_x0020_number>
<Colour_x0020_1>uncoloured</Colour_x0020_1>
<Colour_x0020_2>uncoloured</Colour_x0020_2>
<Material>plaster</Material>
<Surface>varnished</Surface>
<Surround>none</Surround>
<Condition_x003A__x0020_fineness>fine</Condition_x003A__x0020_fineness>
<Condition_x003A__x0020_completeness>damage to design and legend</Condition_x003A__x0020_completeness>
<Covering>none</Covering>
<Notes>Held in Archives Nationales Flandre no. 5755</Notes>
<MyImage>Guillaume1AN.jpg</MyImage>
<Figure_x0020_number>64</Figure_x0020_number>
</Cast>
<Cast>
<ID>57</ID>
<Identifier>Jean1</Identifier>
<Location>Archives Nationales, Paris</Location>
<Accession_x002F_Collection_x0020_number>Service des Sceaux; SC/Flandre 5752</Accession_x002F_Collection_x0020_number>
<Colour_x0020_1>uncoloured</Colour_x0020_1>
<Colour_x0020_2>uncoloured</Colour_x0020_2>
<Material>plaster</Material>
<Surface>varnished</Surface>
<Surround>none</Surround>
<Condition_x003A__x0020_fineness>fine</Condition_x003A__x0020_fineness>
<Condition_x003A__x0020_completeness>damage to design and legend</Condition_x003A__x0020_completeness>
<Covering>none</Covering>
<Notes>Held in Archives Nationales Flandre no. 5752</Notes>
<MyImage>Jean1ANb.jpg</MyImage>
<Height>84</Height>
<Figure_x0020_number>34</Figure_x0020_number>
</Cast>
<Cast>
<ID>58</ID>
<Identifier>LeJeune1</Identifier>
<Location>Archives Nationales, Paris</Location>
<Accession_x002F_Collection_x0020_number>Service des Sceaux; SC/Bourgogne 877</Accession_x002F_Collection_x0020_number>
<Colour_x0020_1>uncoloured</Colour_x0020_1>
<Colour_x0020_2>uncoloured</Colour_x0020_2>
<Material>plaster</Material>
<Surface>plain</Surface>
<Surround>none</Surround>
<Condition_x003A__x0020_fineness>clear</Condition_x003A__x0020_fineness>
<Condition_x003A__x0020_completeness>damage to design and legend</Condition_x003A__x0020_completeness>
<Covering>plastic cover</Covering>
<Notes>Held in Archives Nationales Bourgogne no. 877</Notes>
<MyImage>JeuneJ1AN.jpg</MyImage>
<Width>64</Width>
<Figure_x0020_number>38</Figure_x0020_number>
</Cast>
<Cast>
<ID>61</ID>
<Identifier>Lenzol-BorgiaR1</Identifier>
<Location>Archives Nationales, Paris</Location>
<Accession_x002F_Collection_x0020_number>Service des Sceaux; SC/Champagne 1460</Accession_x002F_Collection_x0020_number>
<Colour_x0020_1>uncoloured</Colour_x0020_1>
<Colour_x0020_2>uncoloured</Colour_x0020_2>
<Material>plaster</Material>
<Surface>plain</Surface>
<Surround>none</Surround>
<Condition_x003A__x0020_fineness>faint</Condition_x003A__x0020_fineness>
<Condition_x003A__x0020_completeness>damage to design and legend</Condition_x003A__x0020_completeness>
<Covering>plastic cover</Covering>
<Notes>Held in Archives Nationales Champagne no. 1460.  &apos;Fragment d’un sceau en navette, de 116 et 67 mill. sur cordelettes / de chanvre rouges.  Cire vermeille dans une cuvette de cire vierge.  Arch. / de la Haute-Marne, chapitre de Joinville, G. 97.  Pour juger de ce sceau, / qui est fort beau, il faut voir l’exemplaire complet qui se trouve aux Archives nationales dans la collection de Lorraine sous le nº 454. / C’est d’après ce dernier qu’est faite la description ci-dessous. / &apos;</Notes>
<MyImage>Lenzol-BorgiaR1AN.jpg</MyImage>
<Figure_x0020_number>44</Figure_x0020_number>
</Cast>
<Cast>
<ID>95</ID>
<Identifier>LongueilRO1</Identifier>
<Location>Archives Nationales, Paris</Location>
<Accession_x002F_Collection_x0020_number>Service des Sceaux; SC/Collection Douët d&apos;Arcq 6210</Accession_x002F_Collection_x0020_number>
<Colour_x0020_1>uncoloured</Colour_x0020_1>
<Colour_x0020_2>uncoloured</Colour_x0020_2>
<Material>plaster</Material>
<Surface>varnished</Surface>
<Surround>none</Surround>
<Condition_x003A__x0020_fineness>fine</Condition_x003A__x0020_fineness>
<Condition_x003A__x0020_completeness>damage to design and legend</Condition_x003A__x0020_completeness>
<Covering>none</Covering>
<Notes>M. Douët d&apos;Arcq, &apos;La Collection des Sceaux&apos;, vol. 2, p. 443, no. 6210.  Original held in Arch. de l&apos;Emp. L 368.  &apos;Même provenance que le numéro 6206 - Nota.  ce sceau, d&apos;une belle conservation, offre de trèsjolis détails.&apos;  Size: 107 x 65 ?</Notes>
<MyImage>LongueilRO1.jpg</MyImage>
<Figure_x0020_number>50</Figure_x0020_number>
</Cast>
<Cast>
<ID>56</ID>
<Identifier>LusignanH1</Identifier>
<Location>Archives Nationales, Paris</Location>
<Accession_x002F_Collection_x0020_number>Service des Sceaux; SC/Flandre 5750</Accession_x002F_Collection_x0020_number>
<Colour_x0020_1>uncoloured</Colour_x0020_1>
<Colour_x0020_2>uncoloured</Colour_x0020_2>
<Material>plaster</Material>
<Surface>plain</Surface>
<Surround>none</Surround>
<Condition_x003A__x0020_fineness>clear</Condition_x003A__x0020_fineness>
<Condition_x003A__x0020_completeness>damage to design and legend</Condition_x003A__x0020_completeness>
<Covering>none</Covering>
<Notes>Held in Archives Nationales Flandre no. 5750. &apos;Indulgences accordées à ceux qui visiteront la chapelle du Saint-Sépulcre à Lille. – Arras, 26 septembre 1435.&apos;</Notes>
<MyImage>LusignanH1AN.jpg</MyImage>
<Height>95</Height>
<Figure_x0020_number>35</Figure_x0020_number>
</Cast>
<Cast>
<ID>1</ID>
<Identifier>MediciG1</Identifier>
<Location>Victoria and Albert Museum, London</Location>
<Accession_x002F_Collection_x0020_number>7799-63</Accession_x002F_Collection_x0020_number>
<Colour_x0020_1>uncoloured</Colour_x0020_1>
<Colour_x0020_2>uncoloured</Colour_x0020_2>
<Material>bronze</Material>
<Surface>plain</Surface>
<Surround>none</Surround>
<Condition_x003A__x0020_fineness>fine</Condition_x003A__x0020_fineness>
<Condition_x003A__x0020_completeness>complete</Condition_x003A__x0020_completeness>
<Notes>Bronze cast.  V&amp;A accession number 7799-63.</Notes>
<MyImage>MediciG1VAAcastA.jpg</MyImage>
<Height>106</Height>
<Width>68</Width>
<Figure_x0020_number>76</Figure_x0020_number>
</Cast>
<Cast>
<ID>63</ID>
<Identifier>MellaJ1</Identifier>
<Location>Archives Nationales, Paris</Location>
<Accession_x002F_Collection_x0020_number>Service des Sceaux; SC/Collection Douët d&apos;Arcq 6208</Accession_x002F_Collection_x0020_number>
<Colour_x0020_1>uncoloured</Colour_x0020_1>
<Colour_x0020_2>uncoloured</Colour_x0020_2>
<Material>plaster</Material>
<Surface>plain</Surface>
<Surround>none</Surround>
<Condition_x003A__x0020_fineness>fine</Condition_x003A__x0020_fineness>
<Condition_x003A__x0020_completeness>damage to design and legend</Condition_x003A__x0020_completeness>
<Covering>none</Covering>
<Notes>Size: 90 x 56?  M. Douët d&apos;Arcq, &apos;La Collection des Sceaux&apos;, vol. 2, p. 442, no. 6208.  original held in Arch. de l&apos;Emp. L 368.  &apos;Même provenance que le numéro 6206.&apos;</Notes>
<MyImage>MellaJ1AN.jpg</MyImage>
<Width>56</Width>
<Figure_x0020_number>43</Figure_x0020_number>
</Cast>
<Cast>
<ID>97</ID>
<Identifier>MichieliG2</Identifier>
<Location>Archives Nationales, Paris</Location>
<Accession_x002F_Collection_x0020_number>Service des Sceaux; SC/Collection Douët d&apos;Arcq 6212</Accession_x002F_Collection_x0020_number>
<Colour_x0020_1>uncoloured</Colour_x0020_1>
<Colour_x0020_2>uncoloured</Colour_x0020_2>
<Material>plaster</Material>
<Surface>varnished</Surface>
<Surround>none</Surround>
<Condition_x003A__x0020_fineness>fine</Condition_x003A__x0020_fineness>
<Condition_x003A__x0020_completeness>damage to design and legend</Condition_x003A__x0020_completeness>
<Covering>none</Covering>
<Notes>M. Douët d&apos;Arcq, &apos;La Collection des Sceaux&apos;, vol. 2, p. 443, no. 6212.  Original held in Arch. de l&apos;Emp. L 821.  &apos;Même provenance que le numéro 6211.&apos;  Size: 108 x 62?</Notes>
<MyImage>MichieliG2An.jpg</MyImage>
<Figure_x0020_number>55</Figure_x0020_number>
</Cast>
<Cast>
<ID>65</ID>
<Identifier>MontferratT1</Identifier>
<Location>Archives Nationales, Paris</Location>
<Accession_x002F_Collection_x0020_number>Service des Sceaux; SC/Champagne 1461</Accession_x002F_Collection_x0020_number>
<Colour_x0020_1>uncoloured</Colour_x0020_1>
<Colour_x0020_2>uncoloured</Colour_x0020_2>
<Material>plaster</Material>
<Surface>plain</Surface>
<Surround>none</Surround>
<Condition_x003A__x0020_fineness>clear</Condition_x003A__x0020_fineness>
<Condition_x003A__x0020_completeness>damage to design and legend</Condition_x003A__x0020_completeness>
<Covering>plastic cover</Covering>
<Notes>Size: 104 x 58?  Held in Archives Nationales Champagne no. 1461</Notes>
<MyImage>MontferratT1AN.jpg</MyImage>
<Height>104</Height>
<Figure_x0020_number>54</Figure_x0020_number>
</Cast>
<Cast>
<ID>66</ID>
<Identifier>OrsiniG1</Identifier>
<Location>Archives Nationales, Paris</Location>
<Accession_x002F_Collection_x0020_number>Service des Sceaux; SC/Flandre 5748</Accession_x002F_Collection_x0020_number>
<Colour_x0020_1>uncoloured</Colour_x0020_1>
<Colour_x0020_2>uncoloured</Colour_x0020_2>
<Material>plaster</Material>
<Surface>plain</Surface>
<Surround>none</Surround>
<Condition_x003A__x0020_fineness>fine</Condition_x003A__x0020_fineness>
<Condition_x003A__x0020_completeness>slight damage to legend</Condition_x003A__x0020_completeness>
<Covering>none</Covering>
<Notes>Held in Archives Nationales Flandre no. 5748</Notes>
<MyImage>OrsiniG1AN.jpg</MyImage>
<Height>87</Height>
<Width>54</Width>
<Figure_x0020_number>32</Figure_x0020_number>
</Cast>
<Cast>
<ID>29</ID>
<Identifier>Panciera1</Identifier>
<Location>Archives Nationales, Paris</Location>
<Accession_x002F_Collection_x0020_number>Service des Sceaux; SC/Flandre 5747</Accession_x002F_Collection_x0020_number>
<Colour_x0020_1>uncoloured</Colour_x0020_1>
<Colour_x0020_2>uncoloured</Colour_x0020_2>
<Material>plaster</Material>
<Surface>varnished</Surface>
<Surround>none</Surround>
<Condition_x003A__x0020_fineness>clear</Condition_x003A__x0020_fineness>
<Condition_x003A__x0020_completeness>complete</Condition_x003A__x0020_completeness>
<Covering>none</Covering>
<Notes>Cast from the Archives du Nord, Chambre des Comptes</Notes>
<MyImage>Antoine1AN.jpg</MyImage>
<Height>90</Height>
<Width>60</Width>
<Figure_x0020_number>30</Figure_x0020_number>
</Cast>
<Cast>
<ID>68</ID>
<Identifier>Pierre1</Identifier>
<Location>Archives Nationales, Paris</Location>
<Accession_x002F_Collection_x0020_number>Service des Sceaux; SC/Collection Douët d&apos;Arcq 6203</Accession_x002F_Collection_x0020_number>
<Colour_x0020_1>uncoloured</Colour_x0020_1>
<Colour_x0020_2>uncoloured</Colour_x0020_2>
<Material>plaster</Material>
<Surface>plain</Surface>
<Surround>none</Surround>
<Condition_x003A__x0020_fineness>fine</Condition_x003A__x0020_fineness>
<Condition_x003A__x0020_completeness>complete</Condition_x003A__x0020_completeness>
<Covering>none</Covering>
<Notes>M. Douët d&apos;Arcq, &apos;La Collection des Sceaux&apos;, vol. 2, p. 441, no. 6203.  Original held in Communiqué.  &apos;Ce sceau, qui appartient certainement au Xve siècle, ne paraît pouvoir être attribué qu&apos;à un Petrus Barbus, Venetus, don’t il faut observer qu&apos;il lui donne des armes différentes de celles qu&apos;on voit ici.&apos;</Notes>
<MyImage>Pierre1AN.jpg</MyImage>
<Height>80</Height>
<Width>56</Width>
<Figure_x0020_number>12</Figure_x0020_number>
</Cast>
<Cast>
<ID>100</ID>
<Identifier>PisaniF2</Identifier>
<Location>Society of Antiquaries</Location>
<Accession_x002F_Collection_x0020_number>Seal Cast Collection; Drawer G1</Accession_x002F_Collection_x0020_number>
<Colour_x0020_1>brown</Colour_x0020_1>
<Colour_x0020_2>brown</Colour_x0020_2>
<Material>sealing wax</Material>
<Surface>plain</Surface>
<Surround>none</Surround>
<Condition_x003A__x0020_fineness>fine</Condition_x003A__x0020_fineness>
<Condition_x003A__x0020_completeness>complete</Condition_x003A__x0020_completeness>
<Covering>none</Covering>
<Notes>Measurements are missing</Notes>
<MyImage>PisanoSOAcast.jpg</MyImage>
<Figure_x0020_number>84</Figure_x0020_number>
</Cast>
<Cast>
<ID>75</ID>
<Identifier>RiarioR2</Identifier>
<Location>Archives Nationales, Paris</Location>
<Accession_x002F_Collection_x0020_number>Service des Sceaux; SC/Collection Douët d&apos;Arcq 6218</Accession_x002F_Collection_x0020_number>
<Colour_x0020_1>uncoloured</Colour_x0020_1>
<Colour_x0020_2>uncoloured</Colour_x0020_2>
<Material>plaster</Material>
<Surface>plain</Surface>
<Surround>none</Surround>
<Condition_x003A__x0020_fineness>clear</Condition_x003A__x0020_fineness>
<Condition_x003A__x0020_completeness>fragment</Condition_x003A__x0020_completeness>
<Covering>none</Covering>
<Notes>Size: 103 x 65?  Held in Archives Natonales Douet d&apos;Arcq no. 6218</Notes>
<MyImage>RiarioR2AN.jpg</MyImage>
<Figure_x0020_number>62</Figure_x0020_number>
</Cast>
<Cast>
<ID>76</ID>
<Identifier>RolinJ1</Identifier>
<Location>Archives Nationales, Paris</Location>
<Accession_x002F_Collection_x0020_number>Service des Sceaux; SC/Normandie 2155</Accession_x002F_Collection_x0020_number>
<Colour_x0020_1>uncoloured</Colour_x0020_1>
<Colour_x0020_2>uncoloured</Colour_x0020_2>
<Material>plaster</Material>
<Surface>plain</Surface>
<Surround>none</Surround>
<Condition_x003A__x0020_fineness>fine</Condition_x003A__x0020_fineness>
<Condition_x003A__x0020_completeness>damge to design and legend</Condition_x003A__x0020_completeness>
<Covering>plastic cover</Covering>
<Notes>Size 92 x 58? Held in Archives Nationales Normandie 2155</Notes>
<MyImage>RolinJ2AN.jpg</MyImage>
<Width>58</Width>
<Figure_x0020_number>42</Figure_x0020_number>
</Cast>
<Cast>
<ID>77</ID>
<Identifier>RovereG2</Identifier>
<Location>Archives Nationales, Paris</Location>
<Accession_x002F_Collection_x0020_number>Service des Sceaux; SC/Collection Douët d&apos;Arcq 6214</Accession_x002F_Collection_x0020_number>
<Colour_x0020_1>uncoloured</Colour_x0020_1>
<Colour_x0020_2>uncoloured</Colour_x0020_2>
<Material>plaster</Material>
<Surface>plain</Surface>
<Surround>none</Surround>
<Condition_x003A__x0020_fineness>clear</Condition_x003A__x0020_fineness>
<Condition_x003A__x0020_completeness>damage to design and legend</Condition_x003A__x0020_completeness>
<Covering>none</Covering>
<Notes>Size 120 x 69?  M. Douët d&apos;Arcq, &apos;La Collection des Sceaux&apos;, vol. 2, p. 443, no. 6214.  Original held in Arch. de l&apos;Emp. L 361.  &apos;Appendu à une bulle du cardinal, datée de Tours, 4 des ides d&apos;avril 1481, enfaveur de l&apos;abbaye de Longchamp.&apos;</Notes>
<MyImage>RovereG1ANa.jpg</MyImage>
<Figure_x0020_number>57</Figure_x0020_number>
</Cast>
<Cast>
<ID>4</ID>
<Identifier>Vich1</Identifier>
<Location>Victoria and Albert Museum, London</Location>
<Accession_x002F_Collection_x0020_number>7800-63</Accession_x002F_Collection_x0020_number>
<Colour_x0020_1>uncoloured</Colour_x0020_1>
<Colour_x0020_2>uncoloured</Colour_x0020_2>
<Material>bronze</Material>
<Surface>none</Surface>
<Surround>none</Surround>
<Condition_x003A__x0020_fineness>fine</Condition_x003A__x0020_fineness>
<Condition_x003A__x0020_completeness>complete</Condition_x003A__x0020_completeness>
<Covering>none</Covering>
<Notes>Victoria and Albert Museum accession number 7800-63</Notes>
<MyImage>VichR1VAAcastA.jpg</MyImage>
<Height>107</Height>
<Width>70</Width>
<Figure_x0020_number>75</Figure_x0020_number>
</Cast>
<Cast>
<ID>101</ID>
<Identifier>Viterbo1</Identifier>
<Location>Ashmolean Museum, Oxford</Location>
<Colour_x0020_1>uncoloured</Colour_x0020_1>
<Colour_x0020_2>uncoloured</Colour_x0020_2>
<Material>bronze</Material>
<Surface>plain</Surface>
<Surround>none</Surround>
<Condition_x003A__x0020_fineness>fine</Condition_x003A__x0020_fineness>
<Condition_x003A__x0020_completeness>slight damage to legend</Condition_x003A__x0020_completeness>
<Covering>none</Covering>
<Notes>Generally good cast but quite shallow.  Damage to the bronze on the reverse.  Otherwise, clear details and the names of saints are legible: S • AVGVSTINVS / S • NICOLAVS • TOL</Notes>
<MyImage>ViterboAMcastA.jpg</MyImage>
<Height>115</Height>
<Width>76</Width>
<Figure_x0020_number>77</Figure_x0020_number>
</Cast>
<Cast>
<ID>13</ID>
<Identifier>Wolsey1</Identifier>
<Location>Society of Antiquaries, London</Location>
<Accession_x002F_Collection_x0020_number>Seal Cast Collection; Drawer G1</Accession_x002F_Collection_x0020_number>
<Colour_x0020_1>uncoloured</Colour_x0020_1>
<Colour_x0020_2>uncoloured</Colour_x0020_2>
<Material>plaster</Material>
<Surface>plain</Surface>
<Surround>none</Surround>
<Condition_x003A__x0020_fineness>fair</Condition_x003A__x0020_fineness>
<Condition_x003A__x0020_completeness>damage to design and legend</Condition_x003A__x0020_completeness>
<Covering>none</Covering>
<Notes>Cast held in drawer in G1, Society of Antiquaries of London, Burlington House</Notes>
<MyImage>Wolsey1SOAcast.jpg</MyImage>
<Height>108</Height>
<Width>67</Width>
<Figure_x0020_number>74</Figure_x0020_number>
</Cast>
<Cast>
<ID>84</ID>
<Identifier>Zabarella2</Identifier>
<Location>Archives Nationales, Paris</Location>
<Accession_x002F_Collection_x0020_number>Service des Sceaux; SC/Bourgogne 875</Accession_x002F_Collection_x0020_number>
<Colour_x0020_1>uncoloured</Colour_x0020_1>
<Colour_x0020_2>uncoloured</Colour_x0020_2>
<Material>plaster</Material>
<Surface>plain</Surface>
<Surround>none</Surround>
<Condition_x003A__x0020_fineness>clear</Condition_x003A__x0020_fineness>
<Condition_x003A__x0020_completeness>slight damage to legend</Condition_x003A__x0020_completeness>
<Covering>plastic cover</Covering>
<Notes>Held in Archives Nationales Bourgogne no. 875</Notes>
<MyImage>ZabarellaF2AN.jpg</MyImage>
<Height>90</Height>
<Width>58</Width>
<Figure_x0020_number>31</Figure_x0020_number>
</Cast>
<Cast>
<ID>85</ID>
<Identifier>ZenoGB1</Identifier>
<Location>Archives Nationales, Paris</Location>
<Accession_x002F_Collection_x0020_number>Service des Sceaux; SC/Champagne 1463</Accession_x002F_Collection_x0020_number>
<Colour_x0020_1>uncoloured</Colour_x0020_1>
<Colour_x0020_2>uncoloured</Colour_x0020_2>
<Material>plaster</Material>
<Surface>plain</Surface>
<Surround>none</Surround>
<Condition_x003A__x0020_fineness>faint</Condition_x003A__x0020_fineness>
<Condition_x003A__x0020_completeness>damage to design and legend</Condition_x003A__x0020_completeness>
<Covering>plastic cover</Covering>
<Notes>Size: 100 x 62?  Held in Archives Nationales Champagne no. 1463</Notes>
<MyImage>ZenoGB1AN.jpg</MyImage>
<Width>62</Width>
<Figure_x0020_number>56</Figure_x0020_number>
</Cast>
</dataroot>
